volcano/view/__init__.py
volcano/view/__main__.py
volcano/view/base_web_handler.py
volcano/view/interpolator.py
volcano/view/my_tools.py
volcano/view/period.py
volcano/view/reader_base.py
volcano/view/reader_ecosui_db.py
volcano/view/reader_sim.py
volcano/view/reports.py
volcano/view/the_time.py
volcano/view/time_tools.py
volcano/view/web_exc.py
volcano/view/web_handler.py
volcano_view-0.0.8.data/data/ecosui.json
volcano_view-0.0.8.data/data/sim.json
volcano_view-0.0.8.data/data/version.txt
volcano_view-0.0.8.data/data/www.zip
volcano_view-0.0.8.dist-info/LICENSE
volcano_view-0.0.8.dist-info/METADATA
volcano_view-0.0.8.dist-info/WHEEL
volcano_view-0.0.8.dist-info/top_level.txt
volcano_view-0.0.8.dist-info/RECORD
